glintefy/__init__.py
glintefy/__init__conf__.py
glintefy/__main__.py
glintefy/behaviors.py
glintefy/cli.py
glintefy/config.py
glintefy/config_deploy.py
glintefy/defaultconfig.toml
glintefy/py.typed
glintefy/tools_venv.py
glintefy/scripts/__init__.py
glintefy/scripts/profile_application.py
glintefy/servers/__init__.py
glintefy/servers/review.py
glintefy/servers/review_handlers.py
glintefy/servers/review_tools.py
glintefy/subservers/__init__.py
glintefy/subservers/base.py
glintefy/subservers/common/__init__.py
glintefy/subservers/common/chunked_writer.py
glintefy/subservers/common/files.py
glintefy/subservers/common/git.py
glintefy/subservers/common/issues.py
glintefy/subservers/common/llm_client.py
glintefy/subservers/common/llm_providers.py
glintefy/subservers/common/logging.py
glintefy/subservers/common/mindsets.py
glintefy/subservers/common/protocol.py
glintefy/subservers/fix/__init__.py
glintefy/subservers/review/__init__.py
glintefy/subservers/review/cache_subserver.py
glintefy/subservers/review/deps.py
glintefy/subservers/review/deps_scanners.py
glintefy/subservers/review/docs.py
glintefy/subservers/review/docs_project.py
glintefy/subservers/review/docs_style.py
glintefy/subservers/review/perf.py
glintefy/subservers/review/report.py
glintefy/subservers/review/scope.py
glintefy/subservers/review/security.py
glintefy/subservers/review/cache/__init__.py
glintefy/subservers/review/cache/batch_screener.py
glintefy/subservers/review/cache/cache_models.py
glintefy/subservers/review/cache/hotspot_analyzer.py
glintefy/subservers/review/cache/individual_validator.py
glintefy/subservers/review/cache/pure_function_detector.py
glintefy/subservers/review/cache/source_patcher.py
glintefy/subservers/review/cache/summary_generator.py
glintefy/subservers/review/quality/__init__.py
glintefy/subservers/review/quality/analyzer_results.py
glintefy/subservers/review/quality/architecture.py
glintefy/subservers/review/quality/base.py
glintefy/subservers/review/quality/complexity.py
glintefy-3.0.2.dist-info/METADATA
glintefy-3.0.2.dist-info/WHEEL
glintefy-3.0.2.dist-info/entry_points.txt
glintefy-3.0.2.dist-info/licenses/LICENSE
glintefy-3.0.2.dist-info/RECORD
