Metadata-Version: 2.4
Name: glintefy
Version: 3.0.2
Summary: MCP servers for code review and automated fixing
Project-URL: Homepage, https://github.com/bitranox/glintefy
Project-URL: Repository, https://github.com/bitranox/glintefy.git
Project-URL: Issues, https://github.com/bitranox/glintefy/issues
Author-email: bitranox <bitranox@gmail.com>
License: MIT
License-File: LICENSE
Keywords: ansi,cli,logging,rich,terminal
Classifier: Environment :: Console
Classifier: License :: OSI Approved :: MIT License
Classifier: Operating System :: OS Independent
Classifier: Programming Language :: Python :: 3
Classifier: Programming Language :: Python :: 3 :: Only
Classifier: Programming Language :: Python :: 3.13
Classifier: Typing :: Typed
Requires-Python: >=3.13
Requires-Dist: bandit>=1.9.2
Requires-Dist: gitpython>=3.1.45
Requires-Dist: jinja2>=3.1.6
Requires-Dist: lib-layered-config>=5.1.0
Requires-Dist: mcp>=1.24.0
Requires-Dist: pydantic>=2.12.5
Requires-Dist: pytest>=9.0.2
Requires-Dist: pyyaml>=6.0.3
Requires-Dist: radon>=6.0.1
Requires-Dist: rich-click>=1.9.4
Requires-Dist: urllib3>=2.6.2
Provides-Extra: dev
Requires-Dist: black>=25.12.0; extra == 'dev'
Requires-Dist: build>=1.3.0; extra == 'dev'
Requires-Dist: codecov-cli>=11.2.6; extra == 'dev'
Requires-Dist: import-linter>=2.9; extra == 'dev'
Requires-Dist: mypy>=1.19.1; extra == 'dev'
Requires-Dist: pip-audit>=2.10.0; extra == 'dev'
Requires-Dist: pyright>=1.1.407; extra == 'dev'
Requires-Dist: pytest-asyncio>=1.3.0; extra == 'dev'
Requires-Dist: pytest-cov>=7.0.0; extra == 'dev'
Requires-Dist: pytest-mock>=3.15.1; extra == 'dev'
Requires-Dist: pytest>=9.0.2; extra == 'dev'
Requires-Dist: rtoml>=0.13.0; extra == 'dev'
Requires-Dist: ruff>=0.14.9; extra == 'dev'
Requires-Dist: setuptools>=80.9.0; extra == 'dev'
Requires-Dist: textual>=6.9.0; extra == 'dev'
Requires-Dist: twine>=6.2.0; extra == 'dev'
Provides-Extra: tools
Requires-Dist: bandit>=1.9.2; extra == 'tools'
Requires-Dist: beartype>=0.22.9; extra == 'tools'
Requires-Dist: interrogate>=1.7.0; extra == 'tools'
Requires-Dist: mypy>=1.19.1; extra == 'tools'
Requires-Dist: pylint>=4.0.4; extra == 'tools'
Requires-Dist: radon>=6.0.1; extra == 'tools'
Requires-Dist: ruff>=0.14.9; extra == 'tools'
Requires-Dist: vulture>=2.14; extra == 'tools'
